snovalleyai_image_processing/Derivative.py
snovalleyai_image_processing/Path.py
snovalleyai_image_processing/__init__.py
snovalleyai_image_processing-1.0.4.dist-info/METADATA
snovalleyai_image_processing-1.0.4.dist-info/WHEEL
snovalleyai_image_processing-1.0.4.dist-info/top_level.txt
snovalleyai_image_processing-1.0.4.dist-info/RECORD
