Metadata-Version: 2.1
Name: snovalleyai-image-processing
Version: 1.0.4
Summary: Research tool in image processing
Home-page: https://github.com/jloveric/image-processing
Author: John Loverich
Author-email: john.loverich@gmail.com
License: UNKNOWN
Platform: UNKNOWN
Classifier: Programming Language :: Python :: 3
Classifier: License :: OSI Approved :: MIT License
Classifier: Operating System :: OS Independent
Requires-Dist: numpy
